inventree_tui/__init__.py
inventree_tui/__main__.py
inventree_tui/app.py
inventree_tui/entrypoint.py
inventree_tui/error_screen.py
inventree_tui/model_data_table.py
inventree_tui/settings.py
inventree_tui/status.py
inventree_tui/styles.tcss
inventree_tui/api/__init__.py
inventree_tui/api/base.py
inventree_tui/api/part_search.py
inventree_tui/api/scanner.py
inventree_tui/api/stock_item.py
inventree_tui/api/stock_item_tracking.py
inventree_tui/components/__init__.py
inventree_tui/components/checkbox_set.py
inventree_tui/sound/__init__.py
inventree_tui/sound/chimes.py
inventree_tui/sound/generation.py
inventree_tui/tabs/__init__.py
inventree_tui/tabs/check_in_items_tab.py
inventree_tui/tabs/part_search_tab.py
inventree_tui/tabs/stock_operations_tab.py
inventree_tui/tabs/transfer_items_tab.py
inventree_tui/validation/__init__.py
inventree_tui-0.2.1.dist-info/LICENSE
inventree_tui-0.2.1.dist-info/METADATA
inventree_tui-0.2.1.dist-info/WHEEL
inventree_tui-0.2.1.dist-info/entry_points.txt
inventree_tui-0.2.1.dist-info/top_level.txt
inventree_tui-0.2.1.dist-info/RECORD
