Metadata-Version: 2.1
Name: inventree-tui
Version: 0.2.1
Summary: Terminal UI for InvenTree
Home-page: https://github.com/j-huff/inventree-tui
Classifier: Programming Language :: Python :: 3
Classifier: License :: OSI Approved :: MIT License
Classifier: Operating System :: OS Independent
License-File: LICENSE
Requires-Dist: textual
Requires-Dist: inventree >=0.14.0
Requires-Dist: pydantic
Requires-Dist: pydantic-settings
Requires-Dist: python-dotenv
Requires-Dist: textual-autocomplete ==2.1.0b0
Requires-Dist: fuzzywuzzy
Requires-Dist: setuptools
Requires-Dist: httpx
Requires-Dist: numpy
Requires-Dist: wave
Requires-Dist: pygame
Requires-Dist: gTTS
Requires-Dist: PyYAML
